catchword/__init__.py
catchword/handler.py
catchword/info.py
catchword/main.py
catchword/trie.py
tests/__init__.py
tests/test_handler.py
tests/test_trie.py
catchword-0.1.1.dist-info/METADATA
catchword-0.1.1.dist-info/WHEEL
catchword-0.1.1.dist-info/entry_points.txt
catchword-0.1.1.dist-info/top_level.txt
catchword-0.1.1.dist-info/RECORD
