Metadata-Version: 2.1
Name: catchword
Version: 0.1.1
Author: Jaeho Yang
Author-email: ichuzupikachu@gmail.com
Requires-Python: >3.9
